[
    {
        "name": "Afri Women classy dresses",
        "item_url": "https://files.sophie.co.ke/2023/04/1018296973_4685-1_6281.jpg",
        "description":"Elegant dresses for a perfect and outstanding look. Perfect for all occasions and comfortable fitting. Cute dresses for all seasons",
        "price": "Ksh. 2400/=",
        "id": 1
    },
    {
        "name": "Men Black-Slim Fit ",
        "item_url": "https://files.sophie.co.ke/2023/04/1018296973_4685-1_6281.jpg",
        "description":"These pants are done in a classic design with a belt loop waistband and set-in pockets. The fabric has a unique texture with a barely noticeable raised pattern, which makes these pants look stylish and striking.",
        "price": "Ksh. 1200/=",
        "id": 2
    },
    {
        "name": "Blue Black-Slim Fit ",
        "item_url": "https://files.sophie.co.ke/2023/04/1018296973_4685-1_6281.jpg",
        "description":"These pants are done in a classic design with a belt loop waistband and set-in pockets. The fabric has a unique texture with a barely noticeable raised pattern, which makes these pants look stylish and striking.",
        "price": "Ksh. 1800/=",
        "id": 3
    },
    {
        "name": "Afri Women classy dresses",
        "item_url": "https://files.sophie.co.ke/2023/04/1018296973_4685-1_6281.jpg",
        "description":"Elegant dresses for a perfect and outstanding look. Perfect for all occasions and comfortable fitting. Cute dresses for all seasons",
        "price": "Ksh. 780/=",
        "id": 4
    },
    {
        "name": "Afri Women classy dresses",
        "item_url": "https://files.sophie.co.ke/2023/04/1018296973_4685-1_6281.jpg",
        "description":"Elegant dresses for a perfect and outstanding look. Perfect for all occasions and comfortable fitting. Cute dresses for all seasons",
        "price": "Ksh. 1900/=",
        "id": 5
    }



]